emuparadise_dl/__init__.py
emuparadise_dl/emuparadise_dl.py
emuparadise_dl/helper.py
emuparadise_dl-0.2.5.data/scripts/emuparadise-dl
emuparadise_dl-0.2.5.dist-info/LICENSE
emuparadise_dl-0.2.5.dist-info/METADATA
emuparadise_dl-0.2.5.dist-info/WHEEL
emuparadise_dl-0.2.5.dist-info/top_level.txt
emuparadise_dl-0.2.5.dist-info/RECORD
