Metadata-Version: 2.1
Name: emuparadise-dl
Version: 0.2.5
Summary: Search and Download from rom hosting websites
Home-page: https://github.com/r4yan2/emuparadise-dl
Author: Andrea Grazioso (ray)
Author-email: grazioandre@gmail.com
License: MIT
Keywords: rom emulators retrogaming
Platform: UNKNOWN
Classifier: Programming Language :: Python :: 3
Classifier: License :: OSI Approved :: MIT License
Requires-Dist: requests
Requires-Dist: bs4
Requires-Dist: termcolor
